hyperspectral_gta_data/__init__.py
hyperspectral_gta_data/create_data_dict.py
hyperspectral_gta_data/data_download.py
hyperspectral_gta_data-1.0.4.11.dist-info/LICENSE
hyperspectral_gta_data-1.0.4.11.dist-info/METADATA
hyperspectral_gta_data-1.0.4.11.dist-info/WHEEL
hyperspectral_gta_data-1.0.4.11.dist-info/top_level.txt
hyperspectral_gta_data-1.0.4.11.dist-info/RECORD
